erlpack/__init__.py
erlpack/_packer.cpython-37m-darwin.so
erlpack/_unpacker.cpython-37m-darwin.so
erlpack/constants.py
erlpack/types.py
erlpack-0.3.3.dist-info/COPYING
erlpack-0.3.3.dist-info/LICENSE
erlpack-0.3.3.dist-info/METADATA
erlpack-0.3.3.dist-info/WHEEL
erlpack-0.3.3.dist-info/top_level.txt
erlpack-0.3.3.dist-info/RECORD
