Metadata-Version: 2.1
Name: erlpack
Version: 0.3.3
Summary: A high performance erlang term encoder for Python.
Home-page: http://github.com/discord/erlpack
Author: Jake Heinz
Author-email: jh@discordapp.com
License: Apache 2.0
Platform: UNKNOWN
Requires-Dist: six (==1.12.0)
